ytchanneldata/__init__.py
ytchanneldata/searcher.py
ytchanneldata-0.0.1.dist-info/METADATA
ytchanneldata-0.0.1.dist-info/WHEEL
ytchanneldata-0.0.1.dist-info/top_level.txt
ytchanneldata-0.0.1.dist-info/RECORD
