Metadata-Version: 2.2
Name: ytchanneldata
Version: 0.0.1
Summary: Search youtube channel data and store it
Home-page: https://github.com/aveLucas/yt-data-colector
Author: aveLucas
Author-email: socialucas06@gmail.com
Requires-Python: >=3.8
Dynamic: author
Dynamic: author-email
Dynamic: description
Dynamic: description-content-type
Dynamic: home-page
Dynamic: requires-python
Dynamic: summary
